slayer_in_the_shadows/__init__.py
slayer_in_the_shadows/__main__.py
slayer_in_the_shadows/assets.py
slayer_in_the_shadows/constants.py
slayer_in_the_shadows/game_view.py
slayer_in_the_shadows/handlers.py
slayer_in_the_shadows/assets/levels/demo.tmx
slayer_in_the_shadows/assets/levels/inf_demo.tmx
slayer_in_the_shadows/assets/sounds/enemy_notices.wav
slayer_in_the_shadows/assets/sounds/menu_click.wav
slayer_in_the_shadows/assets/sounds/whoosh.wav
slayer_in_the_shadows/assets/sprites/attacks/slash.png
slayer_in_the_shadows/assets/sprites/enemies/idle-Sheet.png
slayer_in_the_shadows/assets/sprites/enemies/realistic_enemy.png
slayer_in_the_shadows/assets/sprites/map/basic_block.png
slayer_in_the_shadows/assets/sprites/player/idle.png
slayer_in_the_shadows/assets/sprites/player/jump.png
slayer_in_the_shadows/assets/sprites/player/move.png
slayer_in_the_shadows/assets/sprites/player/realistic_player.png
slayer_in_the_shadows/assets/sprites/player/slow_time/clock0.png
slayer_in_the_shadows/assets/sprites/player/slow_time/clock1.png
slayer_in_the_shadows/assets/sprites/player/slow_time/clock2.png
slayer_in_the_shadows/assets/sprites/player/slow_time/clock3.png
slayer_in_the_shadows/assets/sprites/player/slow_time/clock4.png
slayer_in_the_shadows/assets/sprites/spawners/enemy_spawner.png
slayer_in_the_shadows/assets/sprites/spawners/player_spawner.png
slayer_in_the_shadows/assets/tilesets/map.tsx
slayer_in_the_shadows/assets/tilesets/spawners.tsx
slayer_in_the_shadows/sprites/__init__.py
slayer_in_the_shadows/sprites/attacks.py
slayer_in_the_shadows/sprites/bars.py
slayer_in_the_shadows/sprites/character.py
slayer_in_the_shadows/sprites/enemy.py
slayer_in_the_shadows/sprites/player.py
slayer_in_the_shadows-1.0.0.dist-info/LICENSE
slayer_in_the_shadows-1.0.0.dist-info/METADATA
slayer_in_the_shadows-1.0.0.dist-info/WHEEL
slayer_in_the_shadows-1.0.0.dist-info/top_level.txt
slayer_in_the_shadows-1.0.0.dist-info/RECORD
