Metadata-Version: 2.1
Name: slayer-in-the-shadows
Version: 1.0.0
Summary: Lets Build A Game's entry into PyWeek 35
Author-email: Bradley Reynolds <bradley.reynolds@darbia.dev>
License: MIT
Project-URL: repository, https://github.com/letsbuilda/slayer-in-the-shadows/
Project-URL: documentation, https://docs.letsbuilda.dev/slayer-in-the-shadows/
Requires-Python: >=3.10
License-File: LICENSE
Requires-Dist: arcade (==2.6.17)
Provides-Extra: dev
Requires-Dist: black ; extra == 'dev'
Requires-Dist: isort ; extra == 'dev'
Requires-Dist: pylint ; extra == 'dev'
Provides-Extra: docs
Requires-Dist: sphinx ; extra == 'docs'
Requires-Dist: furo ; extra == 'docs'
Requires-Dist: sphinx-autoapi ; extra == 'docs'
Requires-Dist: releases ; extra == 'docs'
Provides-Extra: tests
Requires-Dist: pytest ; extra == 'tests'
